{
    "openapi": "3.0.2",
    "info": {
        "title": "MotivatsiooniApi",
        "version": "1.0.0"
    },
    "paths": {
        "/categories": {
            "get": {
                "tags": [
                    "quotes"
                ],
                "responses": {
                    "200": {
                        "content": {
                            "application/json": {
                                "schema": {
                                    "type": "array",
                                    "items": {
                                        "type": "string"
                                    }
                                },
                                "examples": {
                                    "List of quotes": {
                                        "value": [
                                            "esimene tsitaat",
                                            "teine tsitaat"
                                        ]
                                    }
                                }
                            }
                        },
                        "description": "Returns a list of quotes"
                    }
                },
                "summary": "get list of all quotes from api",
                "description": "Returns a list of all quotes in the api."
            }
        }
    }
}